rulelearn/__init__.py
rulelearn/dise.py
rulelearn/version.py
rulelearn/algorithms/__init__.py
rulelearn/algorithms/r2n/__init__.py
rulelearn/algorithms/r2n/base.py
rulelearn/algorithms/r2n/functions.py
rulelearn/algorithms/r2n/mask.py
rulelearn/algorithms/r2n/preprocessing_layers.py
rulelearn/algorithms/r2n/r2n_algo.py
rulelearn/algorithms/r2n/simple_rulenet.py
rulelearn/algorithms/r2n/training.py
rulelearn/algorithms/r2n/utilities.py
rulelearn/algorithms/rbm/__init__.py
rulelearn/algorithms/rbm/boolean_rule_cg.py
rulelearn/algorithms/rbm/utils.py
rulelearn/algorithms/rbm/rbm/BRCG.py
rulelearn/algorithms/rbm/rbm/GLRM.py
rulelearn/algorithms/rbm/rbm/__init__.py
rulelearn/algorithms/rbm/rbm/beam_search.py
rulelearn/algorithms/rbm/rbm/boolean_rule_cg.py
rulelearn/algorithms/rbm/rbm/features.py
rulelearn/algorithms/rbm/rbm/linear_regression.py
rulelearn/algorithms/rbm/rbm/logistic_regression.py
rulelearn/algorithms/ripper/__init__.py
rulelearn/algorithms/ripper/base.py
rulelearn/algorithms/ripper/binding.py
rulelearn/algorithms/ripper/mdl.py
rulelearn/algorithms/ripper/pruning.py
rulelearn/algorithms/ripper/ripper.py
rulelearn/algorithms/ripper/ripper_ruleset_generator.py
rulelearn/trxf/__init__.py
rulelearn/trxf/metrics.py
rulelearn/trxf/classifier/__init__.py
rulelearn/trxf/classifier/ruleset_classifier.py
rulelearn/trxf/core/__init__.py
rulelearn/trxf/core/boolean_evaluator.py
rulelearn/trxf/core/conjunction.py
rulelearn/trxf/core/dnf_ruleset.py
rulelearn/trxf/core/feature.py
rulelearn/trxf/core/predicate.py
rulelearn/trxf/core/ruleset_generator.py
rulelearn/trxf/core/utils.py
rulelearn/trxf/pmml_export/__init__.py
rulelearn/trxf/pmml_export/__version__.py
rulelearn/trxf/pmml_export/pmml_exporter.py
rulelearn/trxf/pmml_export/models/__init__.py
rulelearn/trxf/pmml_export/models/attribute.py
rulelearn/trxf/pmml_export/models/characteristics.py
rulelearn/trxf/pmml_export/models/data_dictionary.py
rulelearn/trxf/pmml_export/models/mining_schema.py
rulelearn-0.1.2.dist-info/LICENSE
rulelearn-0.1.2.dist-info/METADATA
rulelearn-0.1.2.dist-info/WHEEL
rulelearn-0.1.2.dist-info/top_level.txt
rulelearn-0.1.2.dist-info/RECORD
