Metadata-Version: 2.1
Name: rulelearn
Version: 0.1.2
Summary: This package contains a rule induction toolkit to generate readable and editable rules from data.
Home-page: https://github.com/IBM/rulelearn
Author: Various
Author-email: hvoelzer@acm.org
Classifier: Development Status :: 3 - Alpha
Classifier: License :: OSI Approved :: Apache Software License
Classifier: Programming Language :: Python :: 3.6
Classifier: Programming Language :: Python :: 3.7
Classifier: Programming Language :: Python :: 3.8
Classifier: Programming Language :: Python :: 3.9
Classifier: Programming Language :: Python :: 3.10
License-File: LICENSE
Requires-Dist: pandas
Requires-Dist: numpy
Requires-Dist: scipy
Requires-Dist: numba
Requires-Dist: matplotlib
Requires-Dist: scikit-learn
Requires-Dist: cvxpy
Requires-Dist: torch
Requires-Dist: xmltodict
Requires-Dist: nyoka (==5.4.0)
